setup.py
hapy/__init__.py
hapy/hapy.py
hapy/scripts/delete_job.groovy
hapy_heritrix.egg-info/PKG-INFO
hapy_heritrix.egg-info/SOURCES.txt
hapy_heritrix.egg-info/dependency_links.txt
hapy_heritrix.egg-info/requires.txt
hapy_heritrix.egg-info/top_level.txt