Metadata-Version: 1.1
Name: hapy-heritrix
Version: 0.1.1
Summary: A Python wrapper around the Heritrix API.
Home-page: https://github.com/WilliamMayor/hapy
Author: William Mayor
Author-email: w.mayor@ucl.ac.uk
License: UNKNOWN
Download-URL: https://github.com/WilliamMayor/hapy
Platform: UNKNOWN
